Console/__init__.py
ConsoleIO/__init__.py
IOConsole/__init__.py
IOConsole-0.0.1.dist-info/LICENSE
IOConsole-0.0.1.dist-info/METADATA
IOConsole-0.0.1.dist-info/WHEEL
IOConsole-0.0.1.dist-info/top_level.txt
IOConsole-0.0.1.dist-info/RECORD
