Metadata-Version: 2.1
Name: IOConsole
Version: 0.0.1
Summary: A useful module
Home-page: UNKNOWN
Author: Man Foo
Author-email: foomail@foo.com
License: UNKNOWN
Platform: UNKNOWN
License-File: LICENSE
Requires-Dist: IOPrintStream
